pysolr4.py
setup.py
pysolr4.egg-info/PKG-INFO
pysolr4.egg-info/SOURCES.txt
pysolr4.egg-info/dependency_links.txt
pysolr4.egg-info/requires.txt
pysolr4.egg-info/top_level.txt