Metadata-Version: 1.0
Name: pysolr4
Version: 0.0.1
Summary: A very lightweight Python wrapper for Apache Solr.
Home-page: http://github.com/zeraholladay/pysolr4/
Author: Zera Holladay
Author-email: zeraholladay@gmail.com
License: UNKNOWN
Platform: UNKNOWN
